google_python_cloud_debugger-4.1.dist-info/top_level.txt
google_python_cloud_debugger-4.1.dist-info/RECORD
google_python_cloud_debugger-4.1.dist-info/WHEEL
google_python_cloud_debugger-4.1.dist-info/METADATA
googleclouddebugger/__init__.py
googleclouddebugger/python_breakpoint.py
googleclouddebugger/breakpoints_manager.py
googleclouddebugger/__main__.py
googleclouddebugger/uniquifier_computer.py
googleclouddebugger/version.py
googleclouddebugger/module_utils.py
googleclouddebugger/error_data_visibility_policy.py
googleclouddebugger/collector.py
googleclouddebugger/cdbg_native.cpython-39-x86_64-linux-gnu.so
googleclouddebugger/labels.py
googleclouddebugger/firebase_client.py
googleclouddebugger/appengine_pretty_printers.py
googleclouddebugger/backoff.py
googleclouddebugger/imphook.py
googleclouddebugger/module_explorer.py
googleclouddebugger/glob_data_visibility_policy.py
googleclouddebugger/yaml_data_visibility_config_reader.py
googleclouddebugger/application_info.py
googleclouddebugger/module_search.py
